{
    "name": "＊蒸し帆立＆ちぢみ法蓮草の煮びたし",
    "author": {
        "@type": "Person",
        "name": "ついてるさとちゃん"
    },
    "image": "https://img.cpcdn.com/recipes/3624799/464x260/32c87823910706e98b9f308802814287.jpg?u=3196631&p=1487315818",
    "datePublished": "2016-01-16",
    "description": "タウリンいっぱいで安価なベビーほたて＆ビタミンCの法蓮草で若返りっ✧ థథ ",
    "recipeYield": "小鉢3~4人分",
    "recipeIngredient": [
        {
            "name": "蒸しほたて(写真はベビーほたて)",
            "quantity": "197g"
        },
        {
            "name": "ちぢみ法蓮草",
            "quantity": "1袋"
        },
        {
            "name": "■水",
            "quantity": "100㏄"
        },
        {
            "name": "■酒",
            "quantity": "50㏄"
        },
        {
            "name": "■かき醤油(だし醤油)",
            "quantity": "25㏄"
        },
        {
            "name": "■みりん",
            "quantity": "25㏄"
        },
        {
            "name": "■さとう",
            "quantity": "小2"
        }
    ],
    "recipeInstructions": [
        "小鍋に■印を煮立て、帆立を重ならないように入れ、1~2分サッと煮てそのまま冷ます。",
        "ちぢみ法蓮草：冬限定のほうれん草。葉が厚く、栄養・旨みもギュッ✧味の濃い法蓮草です。＾＾",
        "茎もしっかりしており、くぼんだ所にも細かい土がたくさんついています。手でバラして丁寧に洗います。",
        "外側は大きく、内側が小さいので、ざっくり仕分けておく。",
        "鍋に湯を沸かし、法蓮草を茹でる。\n塩加減は1％：水1.5ℓに対して塩15g。(分量外)→",
        "※葉物を茹でる時の塩は1.5％~が良いとされていますが、今回は加熱時間も短いので、1％にしました。",
        "大きい葉を手で束ねて持ち、茎の部分から入れ、10秒ほどして全体を入れ、葉の部分がしんなりしたら、引き上げて冷水にさらす。",
        "続けて内側の小さい葉と茎をサッと茹で、冷水にさらす。\n",
        "大きい葉は食べやすい大きさにカットして、水気を絞り、厚手のキッチンペーパーで包んでおく。",
        "食べる少し前に、ほたての煮汁ごと、ほうれん草と混ぜたら出来あがり。",
        "2016.3.8\n皆様。有難うございます。(*‾人‾)✧"
    ],
    "cookTime": "PT20M",
    "recipe_id": "3624799",
    "advice": "法蓮草の茹で加減：せっかく栄養価が高いので、私はちょっと歯応えが残るくらいにしています。塩加減など、ご存知の方法でご調整下さい。法蓮草の栄養は熱に弱いので、ほたての煮汁が冷めてから混ぜます。",
    "history": "Myﾚｼﾋﾟ：牡蛎と焼き豆腐の炊いたん・レシピID : 1995440で牡蛎が少ししか無かった時に、ベビーほたても追加したら美味しかったので。今回は豆腐を使ってないので、味つけを薄目に調整して、貝と相性の良い法蓮草を使ってみました。",
    "categories": [
        "今日のご飯・おかず/魚介のおかず/貝類/帆立"
    ],
    "rankings": null,
    "related_keywords": [
        "水",
        "かき醤油",
        "みりん",
        "さとう"
    ],
    "tsukurepo_count": "22",
    "thumbnail": "https://img.cpcdn.com/recipes/3624799/100x141c/699a5f1a6b2054cd477ba2e7b0be488f.jpg?u=3196631&p=1487315818"
}