{
    "name": "簡単とろーりぶり大根",
    "author": {
        "@type": "Person",
        "name": "miisu88"
    },
    "image": "https://img.cpcdn.com/recipes/391964/464x260/0d14c43a4824d1f97dc30892516c293f.jpg?u=497440&p=1214216455",
    "datePublished": "2007-06-19",
    "description": "ぱぱっと簡単にぶり大根ができちゃいます家族に好評の1品です。最近はレシピをもっと簡単にしました 2012.11.14",
    "recipeYield": "2人分",
    "recipeIngredient": [
        {
            "name": "ぶり",
            "quantity": "2、3きれ"
        },
        {
            "name": "大根",
            "quantity": "1/8"
        },
        {
            "name": "★しょうゆ",
            "quantity": "大さじ2"
        },
        {
            "name": "★（みりんはお好みで）",
            "quantity": "大さじ1"
        },
        {
            "name": "★はちみつ（１歳未満不可）又はきび砂糖",
            "quantity": "大さじ2"
        },
        {
            "name": "★水",
            "quantity": "50ccくらい"
        }
    ],
    "recipeInstructions": [
        "ブリに熱湯をかけ臭みとりをする。大根を切りやわらかくなるまで茹でる。圧力鍋だと早いです",
        "★の調味料を鍋に入れ、火を付ける。\nまぜながら、煮立ってきたら\n",
        "鍋にブリを皮の方を下向きに入れ、 ５分ほど煮込んだらブリをひっくり返し、さらに５分ほど煮込む。",
        "火が通ったら大根をいれてタレを絡めるように５分ほど煮込む、タレをぶりと大根にスプーンで何度かかけ、とろーりしてきたら完成",
        "そのまま置いておくと\n味がしみて、 いい色に★"
    ],
    "cookTime": "PT30M",
    "recipe_id": "391964",
    "advice": "途中焦げそうなときは少量水を加えて調整を★そして焦げないように鍋をのぞいてあげてくださいね☻※１歳未満の乳児に蜂蜜は与えないでください",
    "history": "母親から教えてもらったぶりの照り焼きをなるべく簡単に！そして最近はさらに簡単に作ってます★お酒につけなくても、熱湯をかければ臭みはとれます！5歳の息子の大好物！★沢山の作レポ、リピありがとうございます！まだ載せれてない方すみません",
    "categories": [
        "今日のご飯・おかず/魚介のおかず/ぶり",
        "今日のご飯・おかず/野菜のおかず/旬野菜（秋・冬）/大根"
    ],
    "rankings": null,
    "related_keywords": [
        "ぶり大根",
        "ぶり大根 簡単"
    ],
    "tsukurepo_count": "320",
    "thumbnail": "https://img.cpcdn.com/recipes/391964/100x141c/273146d7343056e7a837f9fdee7076da.jpg?u=497440&p=1214216455"
}