{
    "name": "コーンと玉ねぎのふわふわ卵中華スープ",
    "author": {
        "@type": "Person",
        "name": "えいさくん"
    },
    "image": "https://img.cpcdn.com/recipes/384302/464x260/c5d7c9cfdc62cb70070c27e146721a54.jpg?u=489314&p=1214216291",
    "datePublished": "2007-06-04",
    "description": "コーンと玉ねぎの甘みが絶妙なあっさりスープ。スープにとろみをつけることで、簡単にふわふわの卵スープが出来上がります。具材も少なくて節約にもばっちり!!塩分も控えめで健康にもよいです。",
    "recipeYield": "2人分",
    "recipeIngredient": [
        {
            "name": "冷凍スイートコーン",
            "quantity": "お好み量"
        },
        {
            "name": "玉ねぎ",
            "quantity": "中1/2"
        },
        {
            "name": "卵",
            "quantity": "1個"
        },
        {
            "name": "鶏がらスープの素",
            "quantity": "水600mlに対し小さじ4杯"
        },
        {
            "name": "めんつゆ",
            "quantity": "小さじ1～2"
        },
        {
            "name": "水溶き片栗粉",
            "quantity": "適量"
        }
    ],
    "recipeInstructions": [
        "玉ねぎは1cm幅のくし型に切り、半分に切る。",
        "鍋に玉ねぎ、冷凍のコーンを入れ、鶏がらスープの素を加えて玉ねぎが透き通るまで煮る。めんつゆがあれば少量加えると味がしまる。",
        "水溶き片栗粉を加え、好みのスープの硬さになるようとろみをつける。（片栗粉：水は大さじ１：１程度）",
        "卵はよく白身を箸できるように混ぜておき、水を大さじ1杯ほど加えておくのがコツ。一気に鍋に加え、ぱっと花がさいたように卵がひろがったらお玉で混ぜる。※すぐにかきまぜないのがポイント!",
        "卵がふっくらしたらもう出来上がり!!\r\n火にかけすぎないのがポイントです。"
    ],
    "cookTime": "PT10M",
    "recipe_id": "384302",
    "advice": "スープにとろみをつけることで卵がきれいにスープにひろがります。また、卵に水を少量加えておくこともふわふわに仕上げるコツ!!あとは、火をすぐにとめ、硬くなるのを防ぐことです。",
    "history": "おかずからして味噌汁より中華スープが作りたかったのですが、すばやくでき、あっさり食べれる具に玉ねぎとコーンを思いついたので作りました。汁物が大好き!!ってわけではない旦那がおいしそうにごくごく飲んでいたのでそれ以来作っています。いつも冷蔵庫にある材料だし、節約にもなりますよ～。",
    "categories": [
        "今日のご飯・おかず/野菜のおかず/旬野菜（夏）/とうもろこし"
    ],
    "rankings": null,
    "related_keywords": [
        "中華スープ コーン",
        "オニオンスープ 減塩"
    ],
    "tsukurepo_count": "85",
    "thumbnail": "https://img.cpcdn.com/recipes/384302/100x141c/9a09aed511f1a0d8e9fbc8757e1f1960.jpg?u=489314&p=1214216291"
}