{
    "name": "鶏とひよこ豆のトロトロカレー煮",
    "author": {
        "@type": "Person",
        "name": "のりとる"
    },
    "image": "https://img.cpcdn.com/recipes/243957/464x260/dfd06f1d78ff624c066a3d40a832dbca.jpg?u=63994&p=1214212779",
    "datePublished": "2006-03-15",
    "description": "キャベツは脇役なんだけど、甘くてトロトロで存在感充分。手羽元とキャベツから出たスープが美味しくて、後をひいちゃいます。",
    "recipeYield": "２人分",
    "recipeIngredient": [
        {
            "name": "鶏手羽元",
            "quantity": "6本"
        },
        {
            "name": "ひよこ豆（水煮したもの）",
            "quantity": "カップ1/2"
        },
        {
            "name": "キャベツ",
            "quantity": "葉2枚"
        },
        {
            "name": "にんにく",
            "quantity": "1/2片"
        },
        {
            "name": "白ワイン",
            "quantity": "大さじ1"
        },
        {
            "name": "水",
            "quantity": "100cc"
        },
        {
            "name": "カレー粉",
            "quantity": "小さじ1/2"
        },
        {
            "name": "クミンシード",
            "quantity": "小さじ1/2"
        },
        {
            "name": "塩",
            "quantity": "小さじ1/3"
        },
        {
            "name": "粗挽き胡椒",
            "quantity": "適宜"
        },
        {
            "name": "オリーブオイル",
            "quantity": "大さじ1"
        }
    ],
    "recipeInstructions": [
        "キャベツの芯の部分をとって5ｍｍ位の薄切りにします。キャベツの葉は太めの千切りに、にんにくは輪切りにします。",
        "鍋にオリーブオイルをひいて、手羽元を皮目から焼きます。皮がキツネ色になったら、転がして全体に焼き付けます。手羽元にだいたい焼き目がついたら、にんにく、キャベツの芯を入れます。",
        "にんにくの香りがしてきたら、キャベツの葉を入れて軽く炒め合わせます。キャベツがしんなりしたら、白ワインを入れ蓋をして2、３分蒸します。",
        "水分が出てきたら、ひよこ豆とクミンシードを入れて混ぜ合わせ、カレー粉と塩を加え軽く炒めます。カレー粉が全体に混ざったら水を加え蓋をして煮ます。",
        "中火〜弱火で、水分が少なくなるまで煮ます。水分が少なくなったら、胡椒をして出来上がり。",
        "旬の菜の花を茹でて添えてみました。軽くトーストしたバゲットなんかもあいそうです。"
    ],
    "cookTime": null,
    "recipe_id": "243957",
    "advice": "キャベツから甘み、手羽元からスープが出るので、よく炒めてくたくたになるまで煮れば出来上がり。スープの味が足りなければ、チキンコンソメをほんの少〜〜し足して下さい。鶏肉の代わりにウィンナーソーセージで作っても美味しかったです。その時もコンソメ足して下さいね。カレー粉は種類によって風味が異なるので、お好みの量でどうぞ♪",
    "history": "ひよこ豆とカリフラワーのカレー煮を作りたかったけど、お店にカリフラワーが見あたらず・・・。ウチにあった手羽元と春キャベツでカレー煮にしてみました。",
    "categories": [
        "今日のご飯・おかず/野菜のおかず/豆類/ひよこ豆",
        "その他/スパイス＆ハーブ/クミン"
    ],
    "rankings": null,
    "related_keywords": [
        "ひよこ豆"
    ],
    "tsukurepo_count": "28",
    "thumbnail": "https://img.cpcdn.com/recipes/243957/100x141c/393e5ee8ea89855e3c654596799c83c1.jpg?u=63994&p=1214212779"
}