{
    "name": "長ネギナムル@サムギョプサル他韓国料理に",
    "author": {
        "@type": "Person",
        "name": "しるびー１９７８"
    },
    "image": "https://img.cpcdn.com/recipes/1355320/464x260/846f518f0e83facb8d7f739e5e900f4f.jpg?u=2739351&p=1336382990",
    "datePublished": "2011-02-13",
    "description": "コムタン、タッコムタン、サムギョプサル、ポッサム他に。別レシピにそれぞれ作り方があります。よろしければご覧下さい。",
    "recipeYield": "1",
    "recipeIngredient": [
        {
            "name": "長ネギ",
            "quantity": "太１／２本"
        },
        {
            "name": "食べるラー油（普通のでも）",
            "quantity": "大さじ１～"
        },
        {
            "name": "白いりごま",
            "quantity": "大さじ１"
        },
        {
            "name": "砂糖",
            "quantity": "ひとつまみ"
        },
        {
            "name": "ブラックペッパー粗挽き",
            "quantity": "少々"
        }
    ],
    "recipeInstructions": [
        "超簡単！長ネギをせん切り又は斜めに薄くスライスする。一度水にさらす。（さらさなくてもいーです）",
        "水気をよーーーーーく切って下さい。これが一番のポイント！あとは調味料で和えるだけ。",
        "こーんなカンジ！",
        "盛り付けて完成です！なーんにでも使っちゃって！",
        "長ねぎナムル＠サムギョプサル他韓国料理にレシピID：1800844 ",
        "韓国美肌スープ＠牛テールのコムタンクッパID :1335167",
        "寒い冬に@韓国料理鶏タッコムタンクッパレシピID :1343492",
        "簡単韓国焼き肉フライパンでサムギョプサルレシピID :1449638",
        "魚焼き機で簡単！韓国焼き肉サムギョプサルレシピID :1338001",
        "野菜たっぷり！簡単韓国料理茹で豚ポッサムレシピID :1452855",
        "簡単節約韓国料理＠豆もやしの炊き込みご飯レシピID :1477786 にも合いますよ！",
        "残暑に！シェフ直伝やみつき汁無し担々麺レシピID：1556563にも添えちゃいました！",
        "24年4月13日(金)つくれぽ１０人達成し話題入りしました！作って下さった皆様ありがとうございました！",
        "and13日だけで10,000件のアクセスいただきました。",
        "H25年11月26日長ねぎカテゴリいただきました！Thanks！",
        "インスタントな味噌ラーメンにも合いますよ！辛味噌ねぎラーメン！",
        "シェフ直伝！ゆずはちみつ味サムギョプサルレシピID：1776825にもピッタリ！",
        "H29年1月12日つくれぽ100人達成しちゃいました！作ってくださったみなさまThanks！"
    ],
    "cookTime": "PT10M",
    "recipe_id": "1355320",
    "advice": "長ネギが臭いので水に放してます。水気をよく切って下さい。ぎゅっと絞ること。水に放さなくても。",
    "history": "サムギョプサルやポッサムに合う、長ネギのナムルを作りたくて。",
    "categories": [
        "今日のご飯・おかず/野菜のおかず/旬野菜（秋・冬）/長ねぎ"
    ],
    "rankings": [
        "サムギョプサル 6位"
    ],
    "related_keywords": [
        "サムギョプサル",
        "サムギョプサル ネギ",
        "サムギョプサル ねぎ",
        "韓国"
    ],
    "tsukurepo_count": "115",
    "thumbnail": "https://img.cpcdn.com/recipes/1355320/100x141c/66bd2d2fc876992c20714cbbeee1ab49.jpg?u=2739351&p=1336382990"
}