{
    "name": "魚肉ソーセージで和風な卵炒め",
    "author": {
        "@type": "Person",
        "name": "カリメロさま"
    },
    "image": "https://img.cpcdn.com/recipes/2395845/464x260/93ee1552552d6f170cfff47d21a9ca09.jpg?u=6602661&p=1384419740",
    "datePublished": "2013-11-14",
    "description": "超・簡単！朝食やお弁当に☆今日は夕飯のサブおかずにしました！",
    "recipeYield": null,
    "recipeIngredient": [
        {
            "name": "魚肉ソーセージ",
            "quantity": "1本"
        },
        {
            "name": "卵",
            "quantity": "2〜3個"
        },
        {
            "name": "本だしの素",
            "quantity": "小さじ1/2"
        },
        {
            "name": "しょうゆ",
            "quantity": "小さじ1/4"
        },
        {
            "name": "サラダ油",
            "quantity": "小さじ1"
        },
        {
            "name": "(パセリ)",
            "quantity": "飾りです"
        }
    ],
    "recipeInstructions": [
        "魚肉ソーセージを棒状に切る。",
        "卵をほぐし、本だしの素、しょうゆを入れて混ぜる。",
        "フライパンにサラダ油を半量(小さじ1/2)熱して、1.を炒める。",
        "少し焼き目がつくぐらいに。",
        "4.にサラダ油半量(小さじ1/2)を足し入れ、2.を入れてかき混ぜる。\nスクランブルエッグを作るように。"
    ],
    "cookTime": "PT20M",
    "recipe_id": "2395845",
    "advice": "面倒でも、先に魚肉ソーセージを炒めて香ばしくするのがポイント。お好みですが、卵を入れたら、火を通し過ぎないようにすると半熟で美味♡甘い卵焼きの味にしたい場合は、砂糖を追加してください。",
    "history": "昔、祖母がよく作ってくれました(*^^*)祖母は砂糖を入れて、甘い卵焼きの味にしていましたが、ウチは夫が甘い卵焼きが嫌いなので、砂糖なしで。",
    "categories": [
        "今日のご飯・おかず/たまご・大豆加工品/たまご/アレンジたまご料理"
    ],
    "rankings": null,
    "related_keywords": [
        "魚肉ソーセージ 卵"
    ],
    "tsukurepo_count": "29",
    "thumbnail": "https://img.cpcdn.com/recipes/2395845/100x141c/38b8e563abb52e83ac5bab8e6b7eac39.jpg?u=6602661&p=1384419740"
}