{
    "name": "コーンとじゃがいものバター醤油炒め",
    "author": {
        "@type": "Person",
        "name": "りょーーーこ"
    },
    "image": "https://img.cpcdn.com/recipes/2705149/464x260/b60bbf0c6761763764862b7229273365.jpg?u=640986&p=1404961890",
    "datePublished": "2014-07-10",
    "description": "☆96個目の話題入り&れぽ200人感謝☆絶対美味しい組み合わせ❤旦那と息子が取り合いで食べます　笑",
    "recipeYield": "２～３人分",
    "recipeIngredient": [
        {
            "name": "とうもろこし",
            "quantity": "1本"
        },
        {
            "name": "じゃがいも",
            "quantity": "2個"
        },
        {
            "name": "バター",
            "quantity": "2かけ"
        },
        {
            "name": "醤油",
            "quantity": "小さじ2～"
        },
        {
            "name": "塩胡椒",
            "quantity": "少々"
        }
    ],
    "recipeInstructions": [
        "トウモロコシは包丁で実を削ぎ、じゃがいもは皮と芽をとってい1ｃｍ角にカットする。",
        "フライパンにバター1かけを入れ熱し、じゃがいもを炒める。",
        "じゃがいもに竹串を通してすっとなったらコーンとバター1かけを入れさらに炒める。",
        "火を止め醤油を足し香ばしい香りがしたら塩胡椒で味を調えて完成☆",
        "念願のレシピ本を出版させて頂きました❤こちらのレシピも掲載されています♪",
        "2017.5☆\nこちらのレシピ本に掲載して頂きました♪ありがとうございます！",
        "2017.6☆クックパッドニュースに掲載して頂きました✨",
        "2017.11☆こちらのレシピ本に掲載して頂きました。\nありがとうございます✨"
    ],
    "cookTime": "PT10M",
    "recipe_id": "2705149",
    "advice": "醤油やバターはお好みで加減して下さい♪時間がない時はじゃがいもレンチンすると早くできます★じゃがいもなしでもOK　笑お弁当にもピッタリですよ★",
    "history": "旬のとうもろこしを使って、子供から大人まで楽しめるレシピを考えました＾＾",
    "categories": [
        "今日のご飯・おかず/野菜のおかず/旬野菜（夏）/とうもろこし"
    ],
    "rankings": [
        "コーン 2位",
        "とうもろこし 8位",
        "じゃがいも炒め 9位",
        "バター炒め 7位"
    ],
    "related_keywords": [
        "コーン",
        "じゃがいも コーン",
        "じゃがいも",
        "とうもろこし"
    ],
    "tsukurepo_count": "283",
    "thumbnail": "https://img.cpcdn.com/recipes/2705149/100x141c/c92190d778a44f832ac29612fed44725.jpg?u=640986&p=1404961890"
}