{
    "name": "激旨♪お手軽な薄切り豚バラのレタス巻♪",
    "author": {
        "@type": "Person",
        "name": "花の嵐"
    },
    "image": "https://img.cpcdn.com/recipes/1632021/464x260/0ec39b84d7d2c65ce5cac1f8d2a2a13d.jpg?u=3599499&p=1321697794",
    "datePublished": "2011-11-19",
    "description": "お店の豚のレタス巻～もっと食べたくて作ったけど、レタスがたくさん食べれて豚は少し。お得！24.3.25話題入り感謝です♪",
    "recipeYield": "",
    "recipeIngredient": [
        {
            "name": "豚肉（豚バラがおすすめ）",
            "quantity": "適量（２～３枚）"
        },
        {
            "name": "レタス",
            "quantity": "適量（２～３枚）"
        },
        {
            "name": "油",
            "quantity": "適量"
        },
        {
            "name": "塩コショウ",
            "quantity": "適量"
        },
        {
            "name": "大根おろし",
            "quantity": "適量"
        },
        {
            "name": "しそ",
            "quantity": "あれば１枚"
        },
        {
            "name": "ミニトマト",
            "quantity": "あれば１個"
        },
        {
            "name": "ガーリックパウダー",
            "quantity": "あれば適量"
        },
        {
            "name": "かぼすしょう油（またはポン酢）",
            "quantity": "お好みで適量"
        }
    ],
    "recipeInstructions": [
        "豚肉は包丁の背などで、薄く伸ばしておく。（巻きやすいし、火が通りやすいので）",
        "レタスは一口大にちぎる。そのレタスを束ねるように５センチくらい長さのレタスもとっておく。",
        "小さくちぎったレタスを重ね、５センチほどのレタスでくるくるっとまく。（まとめる感じ）",
        "熱したフライパンに油を入れ、中火の弱火でレタスを巻いた豚肉を閉じてる方を下にして焼いていく。",
        "巻いたレタスを広げた豚肉にのせて巻いていく。",
        "少し焼き目をつけながら、数回ひっくりかえして、きれいに焼いていく。塩コショウとお好みでガーリックパウダーをふる。",
        "豚肉が焼けたら完成。大根おろしを添えて、お好みでかぼすしょう油、または、ポン酢でいただく。そのままでもいけます！"
    ],
    "cookTime": "PT20M",
    "recipe_id": "1632021",
    "advice": "レタスはちぎりレタスをまとめると豚肉で巻くときに巻きやすいです。豚肉はカリッと焼いた方がおいしいです。",
    "history": "昨日飲み屋さんで頼んだらすごくおいしかったのでお腹いっぱい食べたくなって作りました。",
    "categories": [
        "今日のご飯・おかず/お肉のおかず/豚肉/豚薄切り肉"
    ],
    "rankings": null,
    "related_keywords": [
        "薄切り豚"
    ],
    "tsukurepo_count": "487",
    "thumbnail": "https://img.cpcdn.com/recipes/1632021/100x141c/a1c8046243bbc625cc3cbc7ea24197fa.jpg?u=3599499&p=1321697794"
}