{
    "name": "風邪に☆簡単！卵のシンプル雑炊☆",
    "author": {
        "@type": "Person",
        "name": "デイジーパンジー"
    },
    "image": "https://img.cpcdn.com/recipes/2737374/464x260/f918640f8e729bf8451acf2816cf1884.jpg?u=7371089&p=1407338211",
    "datePublished": "2014-08-19",
    "description": "♡話題入り♡感謝♡体の調子が悪い時や食欲がない時に☆簡単10分！優しい味の雑炊をどーぞ！お好みでねぎを♪",
    "recipeYield": "一人分",
    "recipeIngredient": [
        {
            "name": "ごはん",
            "quantity": "お茶碗1杯"
        },
        {
            "name": "卵",
            "quantity": "1個"
        },
        {
            "name": "ねぎ(お好みで)",
            "quantity": "適量"
        },
        {
            "name": "●水",
            "quantity": "250ml"
        },
        {
            "name": "●醤油",
            "quantity": "小さじ 1"
        },
        {
            "name": "●だしの素",
            "quantity": "小さじ 1/2"
        },
        {
            "name": "●塩",
            "quantity": "少々"
        }
    ],
    "recipeInstructions": [
        "調味料全てを鍋に入れて火にかける。\n卵を溶いておく。",
        "鍋が沸騰したらご飯とねぎ(お好みで)を投入し、お好みの固さになるまでふつふつ煮込む。固めの場合はご飯投入後沸騰したらok",
        "卵を回しながら入れて、沸騰してしばらくしたら火を止め蓋をして2~3 分蒸らし、卵が固まったら軽く混ぜて出来上がり☆",
        "2014,11,02 皆さんのお陰で話題入りしました♡感謝♡",
        "2015,4,24 つくれぽ１００達成しました♪いつもありがとうございます♡"
    ],
    "cookTime": "PT10M",
    "recipe_id": "2737374",
    "advice": "※味は体調悪い時様に薄めの味付けです。濃いめにしたい場合は醤油の量で調節してね☆※ご飯を煮込む所(手順2)でお好みのごはんの固さ水分量に調節してね。※卵を入れる時に沸騰している事を確認してね！",
    "history": "体調が悪い時やお腹の調子が悪い時に作ります。",
    "categories": [
        "今日のご飯・おかず/ごはんもの/リゾット・雑炊類/雑炊・おじや"
    ],
    "rankings": [
        "卵雑炊 8位",
        "卵ぞうすい 8位"
    ],
    "related_keywords": [
        "雑炊",
        "雑炊 風邪",
        "雑炊 簡単",
        "風邪に効く 雑炊"
    ],
    "tsukurepo_count": "425",
    "thumbnail": "https://img.cpcdn.com/recipes/2737374/100x141c/f415f72389462c9c5c749db26b580fda.jpg?u=7371089&p=1407338211"
}