{
    "name": "簡単ヘルシー！塩こんぶde卵かけスパ",
    "author": {
        "@type": "Person",
        "name": "ぶぶくん"
    },
    "image": "https://img.cpcdn.com/recipes/345030/464x260/4fda7fbef11e0d6ca3aa01f83bbbfb87.jpg?u=311561&p=1214215046",
    "datePublished": "2007-03-16",
    "description": "卵かけご飯のパスタバージョン！簡単ノンオイルでヘルシーですし、塩こんぶがいい仕事してますよ～♪（H20.1.24写真変更です）",
    "recipeYield": "1人分",
    "recipeIngredient": [
        {
            "name": "スパゲティ",
            "quantity": "80～100g"
        },
        {
            "name": "卵",
            "quantity": "1個"
        },
        {
            "name": "塩こんぶ",
            "quantity": "適量"
        },
        {
            "name": "醤油",
            "quantity": "適量"
        },
        {
            "name": "万能ネギ",
            "quantity": "適量"
        },
        {
            "name": "塩",
            "quantity": "少々"
        }
    ],
    "recipeInstructions": [
        "塩少々を入れたたっぷりの熱湯に、パスタを入れて袋の記載時間より若干早めで茹でます。",
        "茹でている間にボールに卵をときほぐし、醤油を入れておきます。万能ねぎは細かく刻んでおきます。",
        "パスタが茹であがったら、ボールに入れて卵液をからめます。お皿に移し、塩こんぶと万能ネギを散らせば出来上がりです♪"
    ],
    "cookTime": "PT10M",
    "recipe_id": "345030",
    "advice": "味付けの醤油と塩こんぶのバランスはお好みでどうぞ♪ 私は塩こんぶ多めが好きです!(^^)!★メンバー様からおそば＋青海苔、うどんでも美味しかったという嬉しい報告がありました（うどんの時は塩を少々足した方がいいそうです）♪これなら時間も短縮出来ていいですね^ ^",
    "history": "キキkikiさんの「塩昆布で卵ご飯♪常識だったらごめんなさい」を食べて、塩昆布と生卵の組み合わせも美味しいと感動しました！それにノンオイルなので、カルボナーラよりヘルシーでダイエット中でもいいと思ったので^^;",
    "categories": [
        "今日のご飯・おかず/パスタ・グラタン/和風パスタ/醤油風味スパ"
    ],
    "rankings": null,
    "related_keywords": [
        "卵かけ パスタ"
    ],
    "tsukurepo_count": "62",
    "thumbnail": "https://img.cpcdn.com/recipes/345030/100x141c/8d1b1f9869ccf2233ae196b88b328900.jpg?u=311561&p=1214215046"
}