{
    "name": "超簡単で大好評！酢油(すゆ)キャベツ♪",
    "author": {
        "@type": "Person",
        "name": "mykym"
    },
    "image": "https://img.cpcdn.com/recipes/1884338/464x260/fa85a6a8ccef05e14310e85ad881e20d.jpg?u=2997584&p=1342351930",
    "datePublished": "2012-07-20",
    "description": "いつどこで作っても大好評です♪キャベツでさっぱりしたものが食べたい時にぜひ！",
    "recipeYield": "4人分",
    "recipeIngredient": [
        {
            "name": "キャベツ",
            "quantity": "1/4玉"
        },
        {
            "name": "にんじん",
            "quantity": "1/4本"
        },
        {
            "name": "玉ねぎ",
            "quantity": "1/4個"
        },
        {
            "name": "★米酢",
            "quantity": "大さじ3"
        },
        {
            "name": "★オリーブオイル(サラダ油でもOK)",
            "quantity": "大さじ3"
        },
        {
            "name": "★砂糖",
            "quantity": "大さじ1"
        },
        {
            "name": "★塩",
            "quantity": "適量"
        }
    ],
    "recipeInstructions": [
        "玉ねぎをできるだけ薄切りに、にんじんは千切りにして大きめのボールに入れ、合わせて塩もみしておきます(水にさらさないで！)",
        "別の器に★の調味料を全て混ぜ、ドレッシングを作っておきます。",
        "キャベツは1センチ程度のざく切りにします。",
        "1のボールに3のキャベツを入れて混ぜ、2のドレッシングとあわせて冷蔵庫で10分程度冷やして完成です！"
    ],
    "cookTime": "PT20M",
    "recipe_id": "1884338",
    "advice": "・とにかく玉ねぎとにんじんは水にさらさないこと！・4で冷やす時にお皿等で重しをすると味がよくなじみます。・2013/02/16話題入りしました！皆さん本当にありがとうございます♪",
    "history": "母が40年位前に雑誌で見たレシピを作りやすくアレンジしたそうです。以来、大好評のレシピです。",
    "categories": [
        "今日のご飯・おかず/野菜のおかず/キャベツ"
    ],
    "rankings": null,
    "related_keywords": [
        "キャベツ 酢"
    ],
    "tsukurepo_count": "39",
    "thumbnail": "https://img.cpcdn.com/recipes/1884338/100x141c/291a3c611c2127f6b75d480b21e64e91.jpg?u=2997584&p=1342351930"
}