{
    "name": "納豆とワカメの突き出し（お通し）",
    "author": {
        "@type": "Person",
        "name": "ロイヤルラテ"
    },
    "image": "https://img.cpcdn.com/recipes/1666524/464x260/cf3ba4d148f6afe10ffe31a02a711314.jpg?u=847486&p=1325856970",
    "datePublished": "2012-01-06",
    "description": "和えるだけの簡単な一品。冷蔵庫にあるものでできちゃいます☆2013/12/4話題入り♡",
    "recipeYield": "4人分",
    "recipeIngredient": [
        {
            "name": "納豆",
            "quantity": "2パック"
        },
        {
            "name": "カットわかめ（乾燥）",
            "quantity": "大さじ3〜4"
        },
        {
            "name": "ちりめんじゃこ",
            "quantity": "大さじ1"
        },
        {
            "name": "納豆のタレ",
            "quantity": "2個"
        },
        {
            "name": "麺つゆ（ストレート）",
            "quantity": "小さじ2"
        },
        {
            "name": "マヨネーズ",
            "quantity": "小さじ1/2"
        }
    ],
    "recipeInstructions": [
        "乾燥わかめを水で戻し、材料をすべてボウルなどで混ぜて小鉢に盛りつければ完成☆",
        "2013/12/4\n話題入りしました♡\n作って下さった方どうもありがとうございます♫"
    ],
    "cookTime": "PT5M",
    "recipe_id": "1666524",
    "advice": "ワカメの量は割と適当なのでお好みで調整して下さい。マヨネーズはかなり控えめ。隠し味程度に☆麺つゆの代わりにだし醤油でも良いです（甘口の醤油がオススメ）。突き出し（お通し）に出す程度の量なのでかなり小さな小鉢です。",
    "history": "何か一品欲しいな、と思って適当に和えたら美味しかったのでメモしておきます。",
    "categories": [
        "今日のご飯・おかず/たまご・大豆加工品/納豆"
    ],
    "rankings": null,
    "related_keywords": [
        "お通し",
        "突き出し",
        "簡単 お通し"
    ],
    "tsukurepo_count": "29",
    "thumbnail": "https://img.cpcdn.com/recipes/1666524/100x141c/8015dfad8127b8f43a89b4eaa450d5f3.jpg?u=847486&p=1325856970"
}